nodemanager-0.1.1.dist-info/METADATA
nodemanager-0.1.1.dist-info/WHEEL
nodemanager-0.1.1.dist-info/licenses/LICENSE
nodemanager/__init__.py
nodemanager/nodemanager.cpython-311-x86_64-linux-gnu.so
nodemanager-0.1.1.dist-info/RECORD
