Metadata-Version: 2.3
Name: nodemanager
Version: 0.1.1
Classifier: Programming Language :: Rust
Classifier: Programming Language :: Python :: Implementation :: CPython
Classifier: Programming Language :: Python :: Implementation :: PyPy
Classifier: Topic :: Software Development
Classifier: Topic :: Scientific/Engineering
License-File: LICENSE
Summary: Creating a peer-to-peer network 
Author-email: Cyrille Kenfack <cyrille.kenfack@inria.fr>
Requires-Python: >=3.8
